corr_shap/CorrExplainer.py
corr_shap/__init__.py
corr_shap/sampling/CopulaEmpiricalStrategy.py
corr_shap/sampling/CopulaStrategy.py
corr_shap/sampling/EmpiricalStrategy.py
corr_shap/sampling/GaussEmpiricalStrategy.py
corr_shap/sampling/GaussStrategy.py
corr_shap/sampling/SamplingStrategy.py
corr_shap/sampling/__init__.py
corr_shap/sampling/sampling_factory.py
corr_shap-0.0.2.dist-info/LICENSE
corr_shap-0.0.2.dist-info/METADATA
corr_shap-0.0.2.dist-info/WHEEL
corr_shap-0.0.2.dist-info/top_level.txt
corr_shap-0.0.2.dist-info/RECORD
