Metadata-Version: 2.1
Name: corr-shap
Version: 0.0.2
Summary: This package is an extension of the KernelExplainer of shap package that explains the output of any machine learning model, taking into account dependencies between features. 
Keywords: shap,shapley,dependent,correlated,corr_shap,xai,explainable artificial intelligence
License-File: LICENSE
Requires-Dist: shap
Requires-Dist: statsmodels
Requires-Dist: numpy
Requires-Dist: scikit-learn
Requires-Dist: pandas
Requires-Dist: scipy
Requires-Dist: slicer
